xinspect/__init__.py
xinspect/auto_argparse.py
xinspect/autogen.py
xinspect/dynamic_kwargs.py
xinspect/static_kwargs.py
xinspect-0.4.0.dist-info/LICENSE
xinspect-0.4.0.dist-info/METADATA
xinspect-0.4.0.dist-info/WHEEL
xinspect-0.4.0.dist-info/top_level.txt
xinspect-0.4.0.dist-info/RECORD
